HelloBikeLibrary/__init__.py
HelloBikeLibrary/base.py
HelloBikeLibrary/basic_fun.py
HelloBikeLibrary/common.py
HelloBikeLibrary/con_mysql.py
HelloBikeLibrary/data_conversion.py
HelloBikeLibrary/get_thirdInfo.py
HelloBikeLibrary/request.py
HelloBikeLibrary/version.py
HelloBikeLibrary-1.4.3.dist-info/METADATA
HelloBikeLibrary-1.4.3.dist-info/WHEEL
HelloBikeLibrary-1.4.3.dist-info/top_level.txt
HelloBikeLibrary-1.4.3.dist-info/RECORD
